.coveragerc
.gitignore
.pre-commit-config.yaml
AUTHORS.rst
CHANGELOG.rst
LICENSE.txt
README.md
goal.py
pyproject.toml
setup.cfg
setup.py
test-requirements.txt
tox.ini
wercker.yml
.github/workflows/build_package.yml
.github/workflows/launch_tests.yml
docs/Makefile
docs/authors.rst
docs/changelog.rst
docs/conf.py
docs/index.rst
docs/license.rst
docs/_static/.gitignore
example/client.py
example/requirements.txt
example/webhook.py
src/clustaar/__init__.py
src/clustaar.webhook.egg-info/PKG-INFO
src/clustaar.webhook.egg-info/SOURCES.txt
src/clustaar.webhook.egg-info/dependency_links.txt
src/clustaar.webhook.egg-info/not-zip-safe
src/clustaar.webhook.egg-info/requires.txt
src/clustaar.webhook.egg-info/top_level.txt
src/clustaar/webhook/__init__.py
src/clustaar/webhook/constants.py
src/clustaar/webhook/events.py
src/clustaar/webhook/events_handler.py
src/clustaar/webhook/filters.py
src/clustaar/webhook/monkey_patch.py
src/clustaar/webhook/webhook.py
src/clustaar/webhook/falcon/__init__.py
src/clustaar/webhook/falcon/http_request.py
src/clustaar/webhook/falcon/http_response.py
src/clustaar/webhook/middlewares/__init__.py
src/clustaar/webhook/middlewares/authenticators.py
src/clustaar/webhook/middlewares/basic_authentication_middleware.py
src/clustaar/webhook/middlewares/replay_prevention_middleware.py
src/clustaar/webhook/middlewares/validate_signature_middleware.py
src/clustaar/webhook/routing/__init__.py
src/clustaar/webhook/routing/route.py
src/clustaar/webhook/routing/router.py
tests/conftest.py
tests/resources/webhook_request.json
tests/utils/__init__.py
tests/utils/factory.py
tests/webhook/test_events_handler.py
tests/webhook/test_webhook.py
tests/webhook/falcon/test_http_request.py
tests/webhook/falcon/test_http_response.py
tests/webhook/filters/test_json_key_equals.py
tests/webhook/filters/test_json_key_exists.py
tests/webhook/filters/test_json_key_in.py
tests/webhook/filters/test_step_id.py
tests/webhook/middlewares/test_basic_authentication_middleware.py
tests/webhook/middlewares/test_replay_prevention_middleware.py
tests/webhook/middlewares/test_static_authenticator.py
tests/webhook/middlewares/test_validate_signature_middleware.py
tests/webhook/routing/test_route.py
tests/webhook/routing/test_router.py