Metadata-Version: 2.1
Name: clustaar.webhook
Version: 0.1.7
Summary: Clustaar webhook framework
Home-page: https://github.com/Clustaar/clustaar.webhook
Author: Aurélien
Author-email: axel.schafers@clustaar.com
License: mit
Platform: any
Classifier: Development Status :: 4 - Beta
Classifier: Programming Language :: Python
License-File: LICENSE.txt
License-File: AUTHORS.rst
